LICENSE.txt
MANIFEST.in
README.rst
setup.cfg
setup.py
cli_mock/__init__.py
cli_mock/crecord.py
cli_mock/creplay.py
cli_mock/pytest_plugin.py
cli_mock.egg-info/PKG-INFO
cli_mock.egg-info/SOURCES.txt
cli_mock.egg-info/dependency_links.txt
cli_mock.egg-info/entry_points.txt
cli_mock.egg-info/top_level.txt