Metadata-Version: 1.1
Name: cli-mock
Version: 0.2.1
Summary: Mock command line utils by replaying recorded invocations
Home-page: https://github.com/kvas-it/cli-mock
Author: Vasily Kuznetsov
Author-email: kvas.it@gmail.com
License: MIT
Keywords: cli console mock record replay
Platform: UNKNOWN
Classifier: Development Status :: 3 - Alpha
Classifier: Intended Audience :: Developers
Classifier: Topic :: Software Development :: Testing
Classifier: License :: OSI Approved :: MIT License
Classifier: Programming Language :: Python :: 3
Classifier: Programming Language :: Python :: 3.4
Classifier: Programming Language :: Python :: 3.5
